LICENSE
MANIFEST.in
README.md
requirements.txt
setup.py
comimoc/__init__.py
comimoc/helpers.py
comimoc/models.py
comimoc/settings.py
comimoc/views.py
comimoc.egg-info/PKG-INFO
comimoc.egg-info/SOURCES.txt
comimoc.egg-info/dependency_links.txt
comimoc.egg-info/requires.txt
comimoc.egg-info/top_level.txt
comimoc/admin/__init__.py
comimoc/admin/models.py
comimoc/admin/views.py
comimoc/templates/form.html
comimoc/templates/index.html