Metadata-Version: 1.0
Name: comimoc
Version: 0.9.3
Summary: Comimoc backend for Comimoc
Home-page: UNKNOWN
Author: Jérôme Steunou
Author-email: contact@jeromesteunou.net
License: UNKNOWN
Platform: UNKNOWN
